purecpp_meta_dev/__init__.py
purecpp_meta_dev/purecpp_meta_dev.cpython-39-x86_64-linux-gnu.so
purecpp_meta_dev-0.0.400.dist-info/METADATA
purecpp_meta_dev-0.0.400.dist-info/WHEEL
purecpp_meta_dev-0.0.400.dist-info/top_level.txt
purecpp_meta_dev-0.0.400.dist-info/RECORD
